.gitignore
CHANGES.txt
LICENSE.txt
README.rst
setup.cfg
setup.py
tox.ini
anykeystore/__init__.py
anykeystore/compat.py
anykeystore/exceptions.py
anykeystore/interfaces.py
anykeystore/store.py
anykeystore/utils.py
anykeystore.egg-info/PKG-INFO
anykeystore.egg-info/SOURCES.txt
anykeystore.egg-info/dependency_links.txt
anykeystore.egg-info/entry_points.txt
anykeystore.egg-info/not-zip-safe
anykeystore.egg-info/top_level.txt
anykeystore/backends/__init__.py
anykeystore/backends/memcached.py
anykeystore/backends/memory.py
anykeystore/backends/mongodb.py
anykeystore/backends/redis.py
anykeystore/backends/sqla.py
anykeystore/tests/__init__.py
anykeystore/tests/test_store.py
anykeystore/tests/test_utils.py
anykeystore/tests/test_backends/__init__.py
anykeystore/tests/test_backends/test_memcached.py
anykeystore/tests/test_backends/test_memory.py
anykeystore/tests/test_backends/test_mongodb.py
anykeystore/tests/test_backends/test_redis.py
anykeystore/tests/test_backends/test_sqla.py