Metadata-Version: 1.0
Name: anykeystore
Version: 0.1
Summary: A key-value store supporting multiple backends.
Home-page: UNKNOWN
Author: Michael Merickel
Author-email: oss@m.merickel.org
License: MIT
Platform: UNKNOWN
Classifier: Development Status :: 3 - Alpha
Classifier: Intended Audience :: Developers
Classifier: Programming Language :: Python
Classifier: Programming Language :: Python :: 2.6
Classifier: Programming Language :: Python :: 2.7
Classifier: Topic :: Database
Classifier: License :: OSI Approved :: MIT License
